{
  "$type": "Comindware.Platform.Contracts.ToolbarModel, Comindware.Platform.Contracts",
  "GlobalAlias": {
    "$type": "Comindware.Platform.Contracts.GlobalAlias, Comindware.Platform.Contracts",
    "Type": "Toolbar",
    "Owner": "TemplateForAD",
    "Alias": "defaultListToolbar"
  },
  "Name": "Toolbar for lists",
  "IsDefaultForLists": true,
  "IsDefaultForForms": false,
  "IsDefaultForProcess": false,
  "IsDefaultForProcessDesigner": false,
  "IsDefaultForTaskLists": false,
  "Items": {
    "$type": "System.Collections.Generic.List`1[[Comindware.Platform.Contracts.ToolbarItemModel, Comindware.Platform.Contracts]], mscorlib",
    "$values": [
      {
        "$type": "Comindware.Platform.Contracts.ToolbarItemModel, Comindware.Platform.Contracts",
        "UserCommandGlobalAlias": {
          "$type": "Comindware.Platform.Contracts.GlobalAlias, Comindware.Platform.Contracts",
          "Type": "UserCommand",
          "Owner": "TemplateForAD",
          "Alias": "include"
        },
        "Name": "Include in template",
        "Order": 0,
        "Type": "Action",
        "IconType": "Plus",
        "Severity": "None"
      },
      {
        "$type": "Comindware.Platform.Contracts.ToolbarItemModel, Comindware.Platform.Contracts",
        "UserCommandGlobalAlias": {
          "$type": "Comindware.Platform.Contracts.GlobalAlias, Comindware.Platform.Contracts",
          "Type": "UserCommand",
          "Owner": "TemplateForAD",
          "Alias": "create"
        },
        "Name": "Create",
        "Order": 1,
        "Type": "Action",
        "IconType": "Plus",
        "Severity": "None"
      },
      {
        "$type": "Comindware.Platform.Contracts.ToolbarItemModel, Comindware.Platform.Contracts",
        "UserCommandGlobalAlias": {
          "$type": "Comindware.Platform.Contracts.GlobalAlias, Comindware.Platform.Contracts",
          "Type": "UserCommand",
          "Owner": "TemplateForAD",
          "Alias": "excludeAccount"
        },
        "Name": "Exclude from template",
        "Order": 2,
        "Type": "Action",
        "IconType": "Minus",
        "Severity": "Major"
      },
      {
        "$type": "Comindware.Platform.Contracts.ToolbarItemModel, Comindware.Platform.Contracts",
        "UserCommandGlobalAlias": {
          "$type": "Comindware.Platform.Contracts.GlobalAlias, Comindware.Platform.Contracts",
          "Type": "UserCommand",
          "Owner": "TemplateForAD",
          "Alias": "deleteAccount"
        },
        "Name": "Delete",
        "Order": 3,
        "Type": "Action",
        "IconType": "Remove",
        "Severity": "Fatal"
      }
    ]
  }
}